[{
  "_id": {
    "$oid": "6648e345d81b52d5a2b8b7ab"
  },
  "sender_id": {
    "$oid": "6648cbeb5161d66fd0e95f11"
  },
  "receiver_id": {
    "$oid": "6648cbeb5161d66fd0e95f51"
  },
  "rating": 1
},
{
  "_id": {
    "$oid": "6648e345d81b52d5a2b8b7ac"
  },
  "sender_id": {
    "$oid": "6648cbeb5161d66fd0e95f13"
  },
  "receiver_id": {
    "$oid": "6648cbeb5161d66fd0e95f3c"
  },
  "rating": 5
},
{
  "_id": {
    "$oid": "6648e345d81b52d5a2b8b7ad"
  },
  "sender_id": {
    "$oid": "6648cbeb5161d66fd0e95f0e"
  },
  "receiver_id": {
    "$oid": "6648cbeb5161d66fd0e95f49"
  },
  "rating": 2
},
{
  "_id": {
    "$oid": "6648e345d81b52d5a2b8b7ae"
  },
  "sender_id": {
    "$oid": "6648cbec5161d66fd0e95f92"
  },
  "receiver_id": {
    "$oid": "6648cbeb5161d66fd0e95f4b"
  },
  "rating": 4
},
{
  "_id": {
    "$oid": "6648e345d81b52d5a2b8b7af"
  },
  "sender_id": {
    "$oid": "6648cbec5161d66fd0e95f79"
  },
  "receiver_id": {
    "$oid": "6648cbeb5161d66fd0e95f53"
  },
  "rating": 1
},
{
  "_id": {
    "$oid": "6648e345d81b52d5a2b8b7b0"
  },
  "sender_id": {
    "$oid": "6648cbec5161d66fd0e95f90"
  },
  "receiver_id": {
    "$oid": "6648cbeb5161d66fd0e95f3e"
  },
  "rating": 3
},
{
  "_id": {
    "$oid": "6648e345d81b52d5a2b8b7b1"
  },
  "sender_id": {
    "$oid": "6648cbec5161d66fd0e95f8f"
  },
  "receiver_id": {
    "$oid": "6648cbeb5161d66fd0e95f58"
  },
  "rating": 4
},
{
  "_id": {
    "$oid": "6648e345d81b52d5a2b8b7b2"
  },
  "sender_id": {
    "$oid": "6648cbeb5161d66fd0e95f1a"
  },
  "receiver_id": {
    "$oid": "6648cbeb5161d66fd0e95f49"
  },
  "rating": 1
},
{
  "_id": {
    "$oid": "6648e345d81b52d5a2b8b7b3"
  },
  "sender_id": {
    "$oid": "6648cbec5161d66fd0e95f8d"
  },
  "receiver_id": {
    "$oid": "6648cbeb5161d66fd0e95f52"
  },
  "rating": 3
},
{
  "_id": {
    "$oid": "6648e345d81b52d5a2b8b7b4"
  },
  "sender_id": {
    "$oid": "6648cbec5161d66fd0e95f84"
  },
  "receiver_id": {
    "$oid": "6648cbeb5161d66fd0e95f44"
  },
  "rating": 5
},
{
  "_id": {
    "$oid": "6648e345d81b52d5a2b8b7b5"
  },
  "sender_id": {
    "$oid": "6648cbeb5161d66fd0e95f0a"
  },
  "receiver_id": {
    "$oid": "6648cbeb5161d66fd0e95f3d"
  },
  "rating": 1
},
{
  "_id": {
    "$oid": "6648e345d81b52d5a2b8b7b6"
  },
  "sender_id": {
    "$oid": "6648cbeb5161d66fd0e95f18"
  },
  "receiver_id": {
    "$oid": "6648cbeb5161d66fd0e95f45"
  },
  "rating": 5
},
{
  "_id": {
    "$oid": "6648e345d81b52d5a2b8b7b7"
  },
  "sender_id": {
    "$oid": "6648cbec5161d66fd0e95f91"
  },
  "receiver_id": {
    "$oid": "6648cbeb5161d66fd0e95f3c"
  },
  "rating": 4
},
{
  "_id": {
    "$oid": "6648e345d81b52d5a2b8b7b8"
  },
  "sender_id": {
    "$oid": "6648cbec5161d66fd0e95f7b"
  },
  "receiver_id": {
    "$oid": "6648cbeb5161d66fd0e95f49"
  },
  "rating": 3
},
{
  "_id": {
    "$oid": "6648e345d81b52d5a2b8b7b9"
  },
  "sender_id": {
    "$oid": "6648cbeb5161d66fd0e95f03"
  },
  "receiver_id": {
    "$oid": "6648cbeb5161d66fd0e95f4c"
  },
  "rating": 4
},
{
  "_id": {
    "$oid": "6648e345d81b52d5a2b8b7ba"
  },
  "sender_id": {
    "$oid": "6648cbeb5161d66fd0e95f00"
  },
  "receiver_id": {
    "$oid": "6648cbeb5161d66fd0e95f3d"
  },
  "rating": 1
},
{
  "_id": {
    "$oid": "6648e345d81b52d5a2b8b7bb"
  },
  "sender_id": {
    "$oid": "6648cbec5161d66fd0e95f7f"
  },
  "receiver_id": {
    "$oid": "6648cbeb5161d66fd0e95f4e"
  },
  "rating": 1
},
{
  "_id": {
    "$oid": "6648e345d81b52d5a2b8b7bc"
  },
  "sender_id": {
    "$oid": "6648cbeb5161d66fd0e95f12"
  },
  "receiver_id": {
    "$oid": "6648cbeb5161d66fd0e95f4f"
  },
  "rating": 1
},
{
  "_id": {
    "$oid": "6648e345d81b52d5a2b8b7bd"
  },
  "sender_id": {
    "$oid": "6648cbeb5161d66fd0e95f11"
  },
  "receiver_id": {
    "$oid": "6648cbeb5161d66fd0e95f52"
  },
  "rating": 1
},
{
  "_id": {
    "$oid": "6648e345d81b52d5a2b8b7be"
  },
  "sender_id": {
    "$oid": "6648cbec5161d66fd0e95f89"
  },
  "receiver_id": {
    "$oid": "6648cbeb5161d66fd0e95f4c"
  },
  "rating": 1
},
{
  "_id": {
    "$oid": "6648e345d81b52d5a2b8b7bf"
  },
  "sender_id": {
    "$oid": "6648cbeb5161d66fd0e95f1b"
  },
  "receiver_id": {
    "$oid": "6648cbeb5161d66fd0e95f4b"
  },
  "rating": 2
},
{
  "_id": {
    "$oid": "6648e345d81b52d5a2b8b7c0"
  },
  "sender_id": {
    "$oid": "6648cbec5161d66fd0e95f85"
  },
  "receiver_id": {
    "$oid": "6648cbeb5161d66fd0e95f4e"
  },
  "rating": 2
},
{
  "_id": {
    "$oid": "6648e345d81b52d5a2b8b7c1"
  },
  "sender_id": {
    "$oid": "6648cbeb5161d66fd0e95f1a"
  },
  "receiver_id": {
    "$oid": "6648cbeb5161d66fd0e95f46"
  },
  "rating": 1
},
{
  "_id": {
    "$oid": "6648e345d81b52d5a2b8b7c2"
  },
  "sender_id": {
    "$oid": "6648cbec5161d66fd0e95f87"
  },
  "receiver_id": {
    "$oid": "6648cbeb5161d66fd0e95f3c"
  },
  "rating": 4
},
{
  "_id": {
    "$oid": "6648e345d81b52d5a2b8b7c3"
  },
  "sender_id": {
    "$oid": "6648cbec5161d66fd0e95f92"
  },
  "receiver_id": {
    "$oid": "6648cbeb5161d66fd0e95f42"
  },
  "rating": 1
},
{
  "_id": {
    "$oid": "6648e345d81b52d5a2b8b7c4"
  },
  "sender_id": {
    "$oid": "6648cbeb5161d66fd0e95f14"
  },
  "receiver_id": {
    "$oid": "6648cbeb5161d66fd0e95f4c"
  },
  "rating": 3
},
{
  "_id": {
    "$oid": "6648e345d81b52d5a2b8b7c5"
  },
  "sender_id": {
    "$oid": "6648cbec5161d66fd0e95f88"
  },
  "receiver_id": {
    "$oid": "6648cbeb5161d66fd0e95f4d"
  },
  "rating": 2
},
{
  "_id": {
    "$oid": "6648e345d81b52d5a2b8b7c6"
  },
  "sender_id": {
    "$oid": "6648cbeb5161d66fd0e95f14"
  },
  "receiver_id": {
    "$oid": "6648cbeb5161d66fd0e95f57"
  },
  "rating": 5
},
{
  "_id": {
    "$oid": "6648e345d81b52d5a2b8b7c7"
  },
  "sender_id": {
    "$oid": "6648cbec5161d66fd0e95f88"
  },
  "receiver_id": {
    "$oid": "6648cbeb5161d66fd0e95f3f"
  },
  "rating": 5
},
{
  "_id": {
    "$oid": "6648e345d81b52d5a2b8b7c8"
  },
  "sender_id": {
    "$oid": "6648cbec5161d66fd0e95f7b"
  },
  "receiver_id": {
    "$oid": "6648cbeb5161d66fd0e95f3f"
  },
  "rating": 3
},
{
  "_id": {
    "$oid": "6648e345d81b52d5a2b8b7c9"
  },
  "sender_id": {
    "$oid": "6648cbec5161d66fd0e95f91"
  },
  "receiver_id": {
    "$oid": "6648cbeb5161d66fd0e95f47"
  },
  "rating": 4
},
{
  "_id": {
    "$oid": "6648e345d81b52d5a2b8b7ca"
  },
  "sender_id": {
    "$oid": "6648cbec5161d66fd0e95f7c"
  },
  "receiver_id": {
    "$oid": "6648cbeb5161d66fd0e95f55"
  },
  "rating": 5
},
{
  "_id": {
    "$oid": "6648e345d81b52d5a2b8b7cb"
  },
  "sender_id": {
    "$oid": "6648cbec5161d66fd0e95f82"
  },
  "receiver_id": {
    "$oid": "6648cbeb5161d66fd0e95f49"
  },
  "rating": 3
},
{
  "_id": {
    "$oid": "6648e345d81b52d5a2b8b7cc"
  },
  "sender_id": {
    "$oid": "6648cbeb5161d66fd0e95eff"
  },
  "receiver_id": {
    "$oid": "6648cbeb5161d66fd0e95f3c"
  },
  "rating": 4
},
{
  "_id": {
    "$oid": "6648e345d81b52d5a2b8b7cd"
  },
  "sender_id": {
    "$oid": "6648cbec5161d66fd0e95f94"
  },
  "receiver_id": {
    "$oid": "6648cbeb5161d66fd0e95f57"
  },
  "rating": 5
},
{
  "_id": {
    "$oid": "6648e345d81b52d5a2b8b7ce"
  },
  "sender_id": {
    "$oid": "6648cbec5161d66fd0e95f93"
  },
  "receiver_id": {
    "$oid": "6648cbeb5161d66fd0e95f3f"
  },
  "rating": 5
},
{
  "_id": {
    "$oid": "6648e345d81b52d5a2b8b7cf"
  },
  "sender_id": {
    "$oid": "6648cbec5161d66fd0e95f85"
  },
  "receiver_id": {
    "$oid": "6648cbeb5161d66fd0e95f4f"
  },
  "rating": 4
},
{
  "_id": {
    "$oid": "6648e345d81b52d5a2b8b7d0"
  },
  "sender_id": {
    "$oid": "6648cbec5161d66fd0e95f92"
  },
  "receiver_id": {
    "$oid": "6648cbeb5161d66fd0e95f57"
  },
  "rating": 3
},
{
  "_id": {
    "$oid": "6648e345d81b52d5a2b8b7d1"
  },
  "sender_id": {
    "$oid": "6648cbec5161d66fd0e95f8c"
  },
  "receiver_id": {
    "$oid": "6648cbeb5161d66fd0e95f3b"
  },
  "rating": 4
},
{
  "_id": {
    "$oid": "6648e345d81b52d5a2b8b7d2"
  },
  "sender_id": {
    "$oid": "6648cbeb5161d66fd0e95f0d"
  },
  "receiver_id": {
    "$oid": "6648cbeb5161d66fd0e95f52"
  },
  "rating": 5
},
{
  "_id": {
    "$oid": "6648e345d81b52d5a2b8b7d3"
  },
  "sender_id": {
    "$oid": "6648cbec5161d66fd0e95f7d"
  },
  "receiver_id": {
    "$oid": "6648cbeb5161d66fd0e95f51"
  },
  "rating": 2
},
{
  "_id": {
    "$oid": "6648e345d81b52d5a2b8b7d4"
  },
  "sender_id": {
    "$oid": "6648cbeb5161d66fd0e95f17"
  },
  "receiver_id": {
    "$oid": "6648cbeb5161d66fd0e95f3d"
  },
  "rating": 2
},
{
  "_id": {
    "$oid": "6648e345d81b52d5a2b8b7d5"
  },
  "sender_id": {
    "$oid": "6648cbec5161d66fd0e95f86"
  },
  "receiver_id": {
    "$oid": "6648cbeb5161d66fd0e95f46"
  },
  "rating": 4
},
{
  "_id": {
    "$oid": "6648e345d81b52d5a2b8b7d6"
  },
  "sender_id": {
    "$oid": "6648cbeb5161d66fd0e95f04"
  },
  "receiver_id": {
    "$oid": "6648cbeb5161d66fd0e95f53"
  },
  "rating": 5
},
{
  "_id": {
    "$oid": "6648e345d81b52d5a2b8b7d7"
  },
  "sender_id": {
    "$oid": "6648cbec5161d66fd0e95f82"
  },
  "receiver_id": {
    "$oid": "6648cbeb5161d66fd0e95f44"
  },
  "rating": 3
},
{
  "_id": {
    "$oid": "6648e345d81b52d5a2b8b7d8"
  },
  "sender_id": {
    "$oid": "6648cbec5161d66fd0e95f7c"
  },
  "receiver_id": {
    "$oid": "6648cbeb5161d66fd0e95f3c"
  },
  "rating": 1
},
{
  "_id": {
    "$oid": "6648e345d81b52d5a2b8b7d9"
  },
  "sender_id": {
    "$oid": "6648cbeb5161d66fd0e95f0d"
  },
  "receiver_id": {
    "$oid": "6648cbeb5161d66fd0e95f44"
  },
  "rating": 2
},
{
  "_id": {
    "$oid": "6648e345d81b52d5a2b8b7da"
  },
  "sender_id": {
    "$oid": "6648cbec5161d66fd0e95f94"
  },
  "receiver_id": {
    "$oid": "6648cbeb5161d66fd0e95f47"
  },
  "rating": 3
},
{
  "_id": {
    "$oid": "6648e345d81b52d5a2b8b7db"
  },
  "sender_id": {
    "$oid": "6648cbec5161d66fd0e95f8f"
  },
  "receiver_id": {
    "$oid": "6648cbeb5161d66fd0e95f50"
  },
  "rating": 2
},
{
  "_id": {
    "$oid": "6648e345d81b52d5a2b8b7dc"
  },
  "sender_id": {
    "$oid": "6648cbec5161d66fd0e95f8e"
  },
  "receiver_id": {
    "$oid": "6648cbeb5161d66fd0e95f3e"
  },
  "rating": 5
},
{
  "_id": {
    "$oid": "6648e345d81b52d5a2b8b7dd"
  },
  "sender_id": {
    "$oid": "6648cbeb5161d66fd0e95f11"
  },
  "receiver_id": {
    "$oid": "6648cbeb5161d66fd0e95f49"
  },
  "rating": 2
},
{
  "_id": {
    "$oid": "6648e345d81b52d5a2b8b7de"
  },
  "sender_id": {
    "$oid": "6648cbeb5161d66fd0e95f0d"
  },
  "receiver_id": {
    "$oid": "6648cbeb5161d66fd0e95f3d"
  },
  "rating": 5
},
{
  "_id": {
    "$oid": "6648e345d81b52d5a2b8b7df"
  },
  "sender_id": {
    "$oid": "6648cbec5161d66fd0e95f7e"
  },
  "receiver_id": {
    "$oid": "6648cbeb5161d66fd0e95f4e"
  },
  "rating": 1
},
{
  "_id": {
    "$oid": "6648e345d81b52d5a2b8b7e0"
  },
  "sender_id": {
    "$oid": "6648cbeb5161d66fd0e95f0b"
  },
  "receiver_id": {
    "$oid": "6648cbeb5161d66fd0e95f3b"
  },
  "rating": 3
},
{
  "_id": {
    "$oid": "6648e345d81b52d5a2b8b7e1"
  },
  "sender_id": {
    "$oid": "6648cbec5161d66fd0e95f92"
  },
  "receiver_id": {
    "$oid": "6648cbeb5161d66fd0e95f51"
  },
  "rating": 3
},
{
  "_id": {
    "$oid": "6648e345d81b52d5a2b8b7e2"
  },
  "sender_id": {
    "$oid": "6648cbec5161d66fd0e95f85"
  },
  "receiver_id": {
    "$oid": "6648cbeb5161d66fd0e95f4f"
  },
  "rating": 2
},
{
  "_id": {
    "$oid": "6648e345d81b52d5a2b8b7e3"
  },
  "sender_id": {
    "$oid": "6648cbec5161d66fd0e95f93"
  },
  "receiver_id": {
    "$oid": "6648cbeb5161d66fd0e95f3f"
  },
  "rating": 4
},
{
  "_id": {
    "$oid": "6648e345d81b52d5a2b8b7e4"
  },
  "sender_id": {
    "$oid": "6648cbec5161d66fd0e95f7b"
  },
  "receiver_id": {
    "$oid": "6648cbeb5161d66fd0e95f3b"
  },
  "rating": 4
},
{
  "_id": {
    "$oid": "6648e345d81b52d5a2b8b7e5"
  },
  "sender_id": {
    "$oid": "6648cbec5161d66fd0e95f7f"
  },
  "receiver_id": {
    "$oid": "6648cbeb5161d66fd0e95f55"
  },
  "rating": 2
},
{
  "_id": {
    "$oid": "6648e345d81b52d5a2b8b7e6"
  },
  "sender_id": {
    "$oid": "6648cbeb5161d66fd0e95f0b"
  },
  "receiver_id": {
    "$oid": "6648cbeb5161d66fd0e95f53"
  },
  "rating": 2
},
{
  "_id": {
    "$oid": "6648e345d81b52d5a2b8b7e7"
  },
  "sender_id": {
    "$oid": "6648cbec5161d66fd0e95f89"
  },
  "receiver_id": {
    "$oid": "6648cbeb5161d66fd0e95f49"
  },
  "rating": 2
},
{
  "_id": {
    "$oid": "6648e345d81b52d5a2b8b7e8"
  },
  "sender_id": {
    "$oid": "6648cbec5161d66fd0e95f83"
  },
  "receiver_id": {
    "$oid": "6648cbeb5161d66fd0e95f46"
  },
  "rating": 5
},
{
  "_id": {
    "$oid": "6648e345d81b52d5a2b8b7e9"
  },
  "sender_id": {
    "$oid": "6648cbec5161d66fd0e95f8f"
  },
  "receiver_id": {
    "$oid": "6648cbeb5161d66fd0e95f4d"
  },
  "rating": 1
},
{
  "_id": {
    "$oid": "6648e345d81b52d5a2b8b7ea"
  },
  "sender_id": {
    "$oid": "6648cbec5161d66fd0e95f94"
  },
  "receiver_id": {
    "$oid": "6648cbeb5161d66fd0e95f47"
  },
  "rating": 1
},
{
  "_id": {
    "$oid": "6648e345d81b52d5a2b8b7eb"
  },
  "sender_id": {
    "$oid": "6648cbeb5161d66fd0e95f0b"
  },
  "receiver_id": {
    "$oid": "6648cbeb5161d66fd0e95f43"
  },
  "rating": 3
},
{
  "_id": {
    "$oid": "6648e345d81b52d5a2b8b7ec"
  },
  "sender_id": {
    "$oid": "6648cbeb5161d66fd0e95f07"
  },
  "receiver_id": {
    "$oid": "6648cbeb5161d66fd0e95f3e"
  },
  "rating": 5
},
{
  "_id": {
    "$oid": "6648e345d81b52d5a2b8b7ed"
  },
  "sender_id": {
    "$oid": "6648cbeb5161d66fd0e95f0e"
  },
  "receiver_id": {
    "$oid": "6648cbeb5161d66fd0e95f4f"
  },
  "rating": 2
},
{
  "_id": {
    "$oid": "6648e345d81b52d5a2b8b7ee"
  },
  "sender_id": {
    "$oid": "6648cbec5161d66fd0e95f7c"
  },
  "receiver_id": {
    "$oid": "6648cbeb5161d66fd0e95f4d"
  },
  "rating": 1
},
{
  "_id": {
    "$oid": "6648e345d81b52d5a2b8b7ef"
  },
  "sender_id": {
    "$oid": "6648cbec5161d66fd0e95f77"
  },
  "receiver_id": {
    "$oid": "6648cbeb5161d66fd0e95f51"
  },
  "rating": 1
},
{
  "_id": {
    "$oid": "6648e345d81b52d5a2b8b7f0"
  },
  "sender_id": {
    "$oid": "6648cbeb5161d66fd0e95f07"
  },
  "receiver_id": {
    "$oid": "6648cbeb5161d66fd0e95f4e"
  },
  "rating": 4
},
{
  "_id": {
    "$oid": "6648e345d81b52d5a2b8b7f1"
  },
  "sender_id": {
    "$oid": "6648cbeb5161d66fd0e95f19"
  },
  "receiver_id": {
    "$oid": "6648cbeb5161d66fd0e95f49"
  },
  "rating": 4
},
{
  "_id": {
    "$oid": "6648e345d81b52d5a2b8b7f2"
  },
  "sender_id": {
    "$oid": "6648cbec5161d66fd0e95f8c"
  },
  "receiver_id": {
    "$oid": "6648cbeb5161d66fd0e95f3f"
  },
  "rating": 3
},
{
  "_id": {
    "$oid": "6648e345d81b52d5a2b8b7f3"
  },
  "sender_id": {
    "$oid": "6648cbec5161d66fd0e95f78"
  },
  "receiver_id": {
    "$oid": "6648cbeb5161d66fd0e95f49"
  },
  "rating": 4
},
{
  "_id": {
    "$oid": "6648e345d81b52d5a2b8b7f4"
  },
  "sender_id": {
    "$oid": "6648cbeb5161d66fd0e95f0b"
  },
  "receiver_id": {
    "$oid": "6648cbeb5161d66fd0e95f48"
  },
  "rating": 5
},
{
  "_id": {
    "$oid": "6648e345d81b52d5a2b8b7f5"
  },
  "sender_id": {
    "$oid": "6648cbec5161d66fd0e95f7a"
  },
  "receiver_id": {
    "$oid": "6648cbeb5161d66fd0e95f57"
  },
  "rating": 2
},
{
  "_id": {
    "$oid": "6648e345d81b52d5a2b8b7f6"
  },
  "sender_id": {
    "$oid": "6648cbeb5161d66fd0e95f10"
  },
  "receiver_id": {
    "$oid": "6648cbeb5161d66fd0e95f40"
  },
  "rating": 2
},
{
  "_id": {
    "$oid": "6648e345d81b52d5a2b8b7f7"
  },
  "sender_id": {
    "$oid": "6648cbec5161d66fd0e95f7c"
  },
  "receiver_id": {
    "$oid": "6648cbeb5161d66fd0e95f49"
  },
  "rating": 3
},
{
  "_id": {
    "$oid": "6648e345d81b52d5a2b8b7f8"
  },
  "sender_id": {
    "$oid": "6648cbec5161d66fd0e95f92"
  },
  "receiver_id": {
    "$oid": "6648cbeb5161d66fd0e95f51"
  },
  "rating": 2
},
{
  "_id": {
    "$oid": "6648e345d81b52d5a2b8b7f9"
  },
  "sender_id": {
    "$oid": "6648cbec5161d66fd0e95f7f"
  },
  "receiver_id": {
    "$oid": "6648cbeb5161d66fd0e95f3c"
  },
  "rating": 4
},
{
  "_id": {
    "$oid": "6648e345d81b52d5a2b8b7fa"
  },
  "sender_id": {
    "$oid": "6648cbec5161d66fd0e95f79"
  },
  "receiver_id": {
    "$oid": "6648cbeb5161d66fd0e95f45"
  },
  "rating": 2
},
{
  "_id": {
    "$oid": "6648e345d81b52d5a2b8b7fb"
  },
  "sender_id": {
    "$oid": "6648cbec5161d66fd0e95f79"
  },
  "receiver_id": {
    "$oid": "6648cbeb5161d66fd0e95f57"
  },
  "rating": 5
},
{
  "_id": {
    "$oid": "6648e345d81b52d5a2b8b7fc"
  },
  "sender_id": {
    "$oid": "6648cbeb5161d66fd0e95f07"
  },
  "receiver_id": {
    "$oid": "6648cbeb5161d66fd0e95f51"
  },
  "rating": 3
},
{
  "_id": {
    "$oid": "6648e345d81b52d5a2b8b7fd"
  },
  "sender_id": {
    "$oid": "6648cbeb5161d66fd0e95f0a"
  },
  "receiver_id": {
    "$oid": "6648cbeb5161d66fd0e95f4c"
  },
  "rating": 3
},
{
  "_id": {
    "$oid": "6648e345d81b52d5a2b8b7fe"
  },
  "sender_id": {
    "$oid": "6648cbeb5161d66fd0e95f0b"
  },
  "receiver_id": {
    "$oid": "6648cbeb5161d66fd0e95f4e"
  },
  "rating": 4
},
{
  "_id": {
    "$oid": "6648e345d81b52d5a2b8b7ff"
  },
  "sender_id": {
    "$oid": "6648cbeb5161d66fd0e95f01"
  },
  "receiver_id": {
    "$oid": "6648cbeb5161d66fd0e95f49"
  },
  "rating": 4
},
{
  "_id": {
    "$oid": "6648e345d81b52d5a2b8b800"
  },
  "sender_id": {
    "$oid": "6648cbeb5161d66fd0e95f00"
  },
  "receiver_id": {
    "$oid": "6648cbeb5161d66fd0e95f4c"
  },
  "rating": 2
},
{
  "_id": {
    "$oid": "6648e345d81b52d5a2b8b801"
  },
  "sender_id": {
    "$oid": "6648cbeb5161d66fd0e95f09"
  },
  "receiver_id": {
    "$oid": "6648cbeb5161d66fd0e95f3f"
  },
  "rating": 1
},
{
  "_id": {
    "$oid": "6648e345d81b52d5a2b8b802"
  },
  "sender_id": {
    "$oid": "6648cbec5161d66fd0e95f8d"
  },
  "receiver_id": {
    "$oid": "6648cbeb5161d66fd0e95f55"
  },
  "rating": 3
},
{
  "_id": {
    "$oid": "6648e345d81b52d5a2b8b803"
  },
  "sender_id": {
    "$oid": "6648cbec5161d66fd0e95f81"
  },
  "receiver_id": {
    "$oid": "6648cbeb5161d66fd0e95f4d"
  },
  "rating": 4
},
{
  "_id": {
    "$oid": "6648e345d81b52d5a2b8b804"
  },
  "sender_id": {
    "$oid": "6648cbec5161d66fd0e95f7c"
  },
  "receiver_id": {
    "$oid": "6648cbeb5161d66fd0e95f51"
  },
  "rating": 5
},
{
  "_id": {
    "$oid": "6648e345d81b52d5a2b8b805"
  },
  "sender_id": {
    "$oid": "6648cbec5161d66fd0e95f94"
  },
  "receiver_id": {
    "$oid": "6648cbeb5161d66fd0e95f40"
  },
  "rating": 1
},
{
  "_id": {
    "$oid": "6648e345d81b52d5a2b8b806"
  },
  "sender_id": {
    "$oid": "6648cbec5161d66fd0e95f94"
  },
  "receiver_id": {
    "$oid": "6648cbeb5161d66fd0e95f49"
  },
  "rating": 2
},
{
  "_id": {
    "$oid": "6648e345d81b52d5a2b8b807"
  },
  "sender_id": {
    "$oid": "6648cbec5161d66fd0e95f7d"
  },
  "receiver_id": {
    "$oid": "6648cbeb5161d66fd0e95f3f"
  },
  "rating": 3
},
{
  "_id": {
    "$oid": "6648e345d81b52d5a2b8b808"
  },
  "sender_id": {
    "$oid": "6648cbeb5161d66fd0e95f0c"
  },
  "receiver_id": {
    "$oid": "6648cbeb5161d66fd0e95f52"
  },
  "rating": 4
},
{
  "_id": {
    "$oid": "6648e345d81b52d5a2b8b809"
  },
  "sender_id": {
    "$oid": "6648cbeb5161d66fd0e95f03"
  },
  "receiver_id": {
    "$oid": "6648cbeb5161d66fd0e95f42"
  },
  "rating": 5
},
{
  "_id": {
    "$oid": "6648e345d81b52d5a2b8b80a"
  },
  "sender_id": {
    "$oid": "6648cbec5161d66fd0e95f8b"
  },
  "receiver_id": {
    "$oid": "6648cbeb5161d66fd0e95f4e"
  },
  "rating": 1
},
{
  "_id": {
    "$oid": "6648e345d81b52d5a2b8b80b"
  },
  "sender_id": {
    "$oid": "6648cbec5161d66fd0e95f7d"
  },
  "receiver_id": {
    "$oid": "6648cbeb5161d66fd0e95f52"
  },
  "rating": 3
},
{
  "_id": {
    "$oid": "6648e345d81b52d5a2b8b80c"
  },
  "sender_id": {
    "$oid": "6648cbec5161d66fd0e95f7e"
  },
  "receiver_id": {
    "$oid": "6648cbeb5161d66fd0e95f4e"
  },
  "rating": 5
},
{
  "_id": {
    "$oid": "6648e345d81b52d5a2b8b80d"
  },
  "sender_id": {
    "$oid": "6648cbeb5161d66fd0e95eff"
  },
  "receiver_id": {
    "$oid": "6648cbeb5161d66fd0e95f45"
  },
  "rating": 1
},
{
  "_id": {
    "$oid": "6648e345d81b52d5a2b8b80e"
  },
  "sender_id": {
    "$oid": "6648cbec5161d66fd0e95f7d"
  },
  "receiver_id": {
    "$oid": "6648cbeb5161d66fd0e95f54"
  },
  "rating": 5
},
{
  "_id": {
    "$oid": "6648e345d81b52d5a2b8b80f"
  },
  "sender_id": {
    "$oid": "6648cbeb5161d66fd0e95f04"
  },
  "receiver_id": {
    "$oid": "6648cbeb5161d66fd0e95f3f"
  },
  "rating": 3
},
{
  "_id": {
    "$oid": "6648e345d81b52d5a2b8b810"
  },
  "sender_id": {
    "$oid": "6648cbec5161d66fd0e95f77"
  },
  "receiver_id": {
    "$oid": "6648cbeb5161d66fd0e95f4d"
  },
  "rating": 1
},
{
  "_id": {
    "$oid": "6648e345d81b52d5a2b8b811"
  },
  "sender_id": {
    "$oid": "6648cbec5161d66fd0e95f8d"
  },
  "receiver_id": {
    "$oid": "6648cbeb5161d66fd0e95f55"
  },
  "rating": 4
},
{
  "_id": {
    "$oid": "6648e345d81b52d5a2b8b812"
  },
  "sender_id": {
    "$oid": "6648cbec5161d66fd0e95f7f"
  },
  "receiver_id": {
    "$oid": "6648cbeb5161d66fd0e95f3f"
  },
  "rating": 4
},
{
  "_id": {
    "$oid": "6648e345d81b52d5a2b8b813"
  },
  "sender_id": {
    "$oid": "6648cbec5161d66fd0e95f77"
  },
  "receiver_id": {
    "$oid": "6648cbeb5161d66fd0e95f4c"
  },
  "rating": 3
},
{
  "_id": {
    "$oid": "6648e345d81b52d5a2b8b814"
  },
  "sender_id": {
    "$oid": "6648cbeb5161d66fd0e95f07"
  },
  "receiver_id": {
    "$oid": "6648cbeb5161d66fd0e95f3d"
  },
  "rating": 3
},
{
  "_id": {
    "$oid": "6648e345d81b52d5a2b8b815"
  },
  "sender_id": {
    "$oid": "6648cbeb5161d66fd0e95f06"
  },
  "receiver_id": {
    "$oid": "6648cbeb5161d66fd0e95f3d"
  },
  "rating": 2
},
{
  "_id": {
    "$oid": "6648e345d81b52d5a2b8b816"
  },
  "sender_id": {
    "$oid": "6648cbec5161d66fd0e95f7c"
  },
  "receiver_id": {
    "$oid": "6648cbeb5161d66fd0e95f4d"
  },
  "rating": 3
},
{
  "_id": {
    "$oid": "6648e345d81b52d5a2b8b817"
  },
  "sender_id": {
    "$oid": "6648cbeb5161d66fd0e95f1c"
  },
  "receiver_id": {
    "$oid": "6648cbeb5161d66fd0e95f43"
  },
  "rating": 1
},
{
  "_id": {
    "$oid": "6648e345d81b52d5a2b8b818"
  },
  "sender_id": {
    "$oid": "6648cbeb5161d66fd0e95f08"
  },
  "receiver_id": {
    "$oid": "6648cbeb5161d66fd0e95f3f"
  },
  "rating": 2
},
{
  "_id": {
    "$oid": "6648e345d81b52d5a2b8b819"
  },
  "sender_id": {
    "$oid": "6648cbec5161d66fd0e95f92"
  },
  "receiver_id": {
    "$oid": "6648cbeb5161d66fd0e95f45"
  },
  "rating": 1
},
{
  "_id": {
    "$oid": "6648e345d81b52d5a2b8b81a"
  },
  "sender_id": {
    "$oid": "6648cbeb5161d66fd0e95f04"
  },
  "receiver_id": {
    "$oid": "6648cbeb5161d66fd0e95f58"
  },
  "rating": 3
},
{
  "_id": {
    "$oid": "6648e345d81b52d5a2b8b81b"
  },
  "sender_id": {
    "$oid": "6648cbeb5161d66fd0e95f03"
  },
  "receiver_id": {
    "$oid": "6648cbeb5161d66fd0e95f4b"
  },
  "rating": 4
},
{
  "_id": {
    "$oid": "6648e345d81b52d5a2b8b81c"
  },
  "sender_id": {
    "$oid": "6648cbeb5161d66fd0e95f0d"
  },
  "receiver_id": {
    "$oid": "6648cbeb5161d66fd0e95f43"
  },
  "rating": 5
},
{
  "_id": {
    "$oid": "6648e345d81b52d5a2b8b81d"
  },
  "sender_id": {
    "$oid": "6648cbec5161d66fd0e95f89"
  },
  "receiver_id": {
    "$oid": "6648cbeb5161d66fd0e95f50"
  },
  "rating": 2
},
{
  "_id": {
    "$oid": "6648e345d81b52d5a2b8b81e"
  },
  "sender_id": {
    "$oid": "6648cbeb5161d66fd0e95f14"
  },
  "receiver_id": {
    "$oid": "6648cbeb5161d66fd0e95f3b"
  },
  "rating": 4
},
{
  "_id": {
    "$oid": "6648e345d81b52d5a2b8b81f"
  },
  "sender_id": {
    "$oid": "6648cbeb5161d66fd0e95f0a"
  },
  "receiver_id": {
    "$oid": "6648cbeb5161d66fd0e95f4a"
  },
  "rating": 3
},
{
  "_id": {
    "$oid": "6648e345d81b52d5a2b8b820"
  },
  "sender_id": {
    "$oid": "6648cbeb5161d66fd0e95f08"
  },
  "receiver_id": {
    "$oid": "6648cbeb5161d66fd0e95f56"
  },
  "rating": 2
},
{
  "_id": {
    "$oid": "6648e345d81b52d5a2b8b821"
  },
  "sender_id": {
    "$oid": "6648cbec5161d66fd0e95f83"
  },
  "receiver_id": {
    "$oid": "6648cbeb5161d66fd0e95f58"
  },
  "rating": 4
},
{
  "_id": {
    "$oid": "6648e345d81b52d5a2b8b822"
  },
  "sender_id": {
    "$oid": "6648cbec5161d66fd0e95f8d"
  },
  "receiver_id": {
    "$oid": "6648cbeb5161d66fd0e95f43"
  },
  "rating": 5
},
{
  "_id": {
    "$oid": "6648e345d81b52d5a2b8b823"
  },
  "sender_id": {
    "$oid": "6648cbeb5161d66fd0e95f01"
  },
  "receiver_id": {
    "$oid": "6648cbeb5161d66fd0e95f54"
  },
  "rating": 5
},
{
  "_id": {
    "$oid": "6648e345d81b52d5a2b8b824"
  },
  "sender_id": {
    "$oid": "6648cbeb5161d66fd0e95f11"
  },
  "receiver_id": {
    "$oid": "6648cbeb5161d66fd0e95f48"
  },
  "rating": 5
},
{
  "_id": {
    "$oid": "6648e345d81b52d5a2b8b825"
  },
  "sender_id": {
    "$oid": "6648cbeb5161d66fd0e95f09"
  },
  "receiver_id": {
    "$oid": "6648cbeb5161d66fd0e95f54"
  },
  "rating": 3
},
{
  "_id": {
    "$oid": "6648e345d81b52d5a2b8b826"
  },
  "sender_id": {
    "$oid": "6648cbec5161d66fd0e95f86"
  },
  "receiver_id": {
    "$oid": "6648cbeb5161d66fd0e95f3f"
  },
  "rating": 2
},
{
  "_id": {
    "$oid": "6648e345d81b52d5a2b8b827"
  },
  "sender_id": {
    "$oid": "6648cbec5161d66fd0e95f8b"
  },
  "receiver_id": {
    "$oid": "6648cbeb5161d66fd0e95f57"
  },
  "rating": 4
},
{
  "_id": {
    "$oid": "6648e345d81b52d5a2b8b828"
  },
  "sender_id": {
    "$oid": "6648cbec5161d66fd0e95f8a"
  },
  "receiver_id": {
    "$oid": "6648cbeb5161d66fd0e95f43"
  },
  "rating": 3
},
{
  "_id": {
    "$oid": "6648e345d81b52d5a2b8b829"
  },
  "sender_id": {
    "$oid": "6648cbeb5161d66fd0e95f0a"
  },
  "receiver_id": {
    "$oid": "6648cbeb5161d66fd0e95f44"
  },
  "rating": 3
},
{
  "_id": {
    "$oid": "6648e345d81b52d5a2b8b82a"
  },
  "sender_id": {
    "$oid": "6648cbeb5161d66fd0e95f09"
  },
  "receiver_id": {
    "$oid": "6648cbeb5161d66fd0e95f44"
  },
  "rating": 1
},
{
  "_id": {
    "$oid": "6648e345d81b52d5a2b8b82b"
  },
  "sender_id": {
    "$oid": "6648cbeb5161d66fd0e95f03"
  },
  "receiver_id": {
    "$oid": "6648cbeb5161d66fd0e95f4f"
  },
  "rating": 5
},
{
  "_id": {
    "$oid": "6648e345d81b52d5a2b8b82c"
  },
  "sender_id": {
    "$oid": "6648cbeb5161d66fd0e95f14"
  },
  "receiver_id": {
    "$oid": "6648cbeb5161d66fd0e95f51"
  },
  "rating": 3
},
{
  "_id": {
    "$oid": "6648e345d81b52d5a2b8b82d"
  },
  "sender_id": {
    "$oid": "6648cbec5161d66fd0e95f89"
  },
  "receiver_id": {
    "$oid": "6648cbeb5161d66fd0e95f3b"
  },
  "rating": 1
},
{
  "_id": {
    "$oid": "6648e345d81b52d5a2b8b82e"
  },
  "sender_id": {
    "$oid": "6648cbeb5161d66fd0e95f02"
  },
  "receiver_id": {
    "$oid": "6648cbeb5161d66fd0e95f47"
  },
  "rating": 1
},
{
  "_id": {
    "$oid": "6648e345d81b52d5a2b8b82f"
  },
  "sender_id": {
    "$oid": "6648cbeb5161d66fd0e95f15"
  },
  "receiver_id": {
    "$oid": "6648cbeb5161d66fd0e95f56"
  },
  "rating": 3
},
{
  "_id": {
    "$oid": "6648e345d81b52d5a2b8b830"
  },
  "sender_id": {
    "$oid": "6648cbec5161d66fd0e95f93"
  },
  "receiver_id": {
    "$oid": "6648cbeb5161d66fd0e95f58"
  },
  "rating": 4
},
{
  "_id": {
    "$oid": "6648e345d81b52d5a2b8b831"
  },
  "sender_id": {
    "$oid": "6648cbec5161d66fd0e95f77"
  },
  "receiver_id": {
    "$oid": "6648cbeb5161d66fd0e95f57"
  },
  "rating": 2
},
{
  "_id": {
    "$oid": "6648e345d81b52d5a2b8b832"
  },
  "sender_id": {
    "$oid": "6648cbec5161d66fd0e95f81"
  },
  "receiver_id": {
    "$oid": "6648cbeb5161d66fd0e95f41"
  },
  "rating": 4
},
{
  "_id": {
    "$oid": "6648e345d81b52d5a2b8b833"
  },
  "sender_id": {
    "$oid": "6648cbec5161d66fd0e95f90"
  },
  "receiver_id": {
    "$oid": "6648cbeb5161d66fd0e95f42"
  },
  "rating": 4
},
{
  "_id": {
    "$oid": "6648e345d81b52d5a2b8b834"
  },
  "sender_id": {
    "$oid": "6648cbeb5161d66fd0e95f01"
  },
  "receiver_id": {
    "$oid": "6648cbeb5161d66fd0e95f52"
  },
  "rating": 1
},
{
  "_id": {
    "$oid": "6648e345d81b52d5a2b8b835"
  },
  "sender_id": {
    "$oid": "6648cbec5161d66fd0e95f7f"
  },
  "receiver_id": {
    "$oid": "6648cbeb5161d66fd0e95f3f"
  },
  "rating": 3
},
{
  "_id": {
    "$oid": "6648e345d81b52d5a2b8b836"
  },
  "sender_id": {
    "$oid": "6648cbeb5161d66fd0e95f0d"
  },
  "receiver_id": {
    "$oid": "6648cbeb5161d66fd0e95f43"
  },
  "rating": 1
},
{
  "_id": {
    "$oid": "6648e345d81b52d5a2b8b837"
  },
  "sender_id": {
    "$oid": "6648cbeb5161d66fd0e95f1b"
  },
  "receiver_id": {
    "$oid": "6648cbeb5161d66fd0e95f48"
  },
  "rating": 5
},
{
  "_id": {
    "$oid": "6648e345d81b52d5a2b8b838"
  },
  "sender_id": {
    "$oid": "6648cbeb5161d66fd0e95f15"
  },
  "receiver_id": {
    "$oid": "6648cbeb5161d66fd0e95f51"
  },
  "rating": 5
},
{
  "_id": {
    "$oid": "6648e345d81b52d5a2b8b839"
  },
  "sender_id": {
    "$oid": "6648cbec5161d66fd0e95f80"
  },
  "receiver_id": {
    "$oid": "6648cbeb5161d66fd0e95f51"
  },
  "rating": 2
},
{
  "_id": {
    "$oid": "6648e345d81b52d5a2b8b83a"
  },
  "sender_id": {
    "$oid": "6648cbec5161d66fd0e95f91"
  },
  "receiver_id": {
    "$oid": "6648cbeb5161d66fd0e95f40"
  },
  "rating": 5
},
{
  "_id": {
    "$oid": "6648e345d81b52d5a2b8b83b"
  },
  "sender_id": {
    "$oid": "6648cbec5161d66fd0e95f87"
  },
  "receiver_id": {
    "$oid": "6648cbeb5161d66fd0e95f3c"
  },
  "rating": 5
},
{
  "_id": {
    "$oid": "6648e345d81b52d5a2b8b83c"
  },
  "sender_id": {
    "$oid": "6648cbec5161d66fd0e95f81"
  },
  "receiver_id": {
    "$oid": "6648cbeb5161d66fd0e95f52"
  },
  "rating": 4
},
{
  "_id": {
    "$oid": "6648e345d81b52d5a2b8b83d"
  },
  "sender_id": {
    "$oid": "6648cbeb5161d66fd0e95f11"
  },
  "receiver_id": {
    "$oid": "6648cbeb5161d66fd0e95f3b"
  },
  "rating": 1
},
{
  "_id": {
    "$oid": "6648e345d81b52d5a2b8b83e"
  },
  "sender_id": {
    "$oid": "6648cbec5161d66fd0e95f78"
  },
  "receiver_id": {
    "$oid": "6648cbeb5161d66fd0e95f3e"
  },
  "rating": 4
},
{
  "_id": {
    "$oid": "6648e345d81b52d5a2b8b83f"
  },
  "sender_id": {
    "$oid": "6648cbec5161d66fd0e95f7e"
  },
  "receiver_id": {
    "$oid": "6648cbeb5161d66fd0e95f48"
  },
  "rating": 2
},
{
  "_id": {
    "$oid": "6648e345d81b52d5a2b8b840"
  },
  "sender_id": {
    "$oid": "6648cbeb5161d66fd0e95f0d"
  },
  "receiver_id": {
    "$oid": "6648cbeb5161d66fd0e95f44"
  },
  "rating": 5
},
{
  "_id": {
    "$oid": "6648e345d81b52d5a2b8b841"
  },
  "sender_id": {
    "$oid": "6648cbec5161d66fd0e95f80"
  },
  "receiver_id": {
    "$oid": "6648cbeb5161d66fd0e95f48"
  },
  "rating": 1
},
{
  "_id": {
    "$oid": "6648e345d81b52d5a2b8b842"
  },
  "sender_id": {
    "$oid": "6648cbec5161d66fd0e95f84"
  },
  "receiver_id": {
    "$oid": "6648cbeb5161d66fd0e95f41"
  },
  "rating": 5
},
{
  "_id": {
    "$oid": "6648e345d81b52d5a2b8b843"
  },
  "sender_id": {
    "$oid": "6648cbec5161d66fd0e95f90"
  },
  "receiver_id": {
    "$oid": "6648cbeb5161d66fd0e95f58"
  },
  "rating": 1
},
{
  "_id": {
    "$oid": "6648e345d81b52d5a2b8b844"
  },
  "sender_id": {
    "$oid": "6648cbec5161d66fd0e95f89"
  },
  "receiver_id": {
    "$oid": "6648cbeb5161d66fd0e95f4a"
  },
  "rating": 5
},
{
  "_id": {
    "$oid": "6648e345d81b52d5a2b8b845"
  },
  "sender_id": {
    "$oid": "6648cbeb5161d66fd0e95f05"
  },
  "receiver_id": {
    "$oid": "6648cbeb5161d66fd0e95f49"
  },
  "rating": 4
},
{
  "_id": {
    "$oid": "6648e345d81b52d5a2b8b846"
  },
  "sender_id": {
    "$oid": "6648cbeb5161d66fd0e95f0a"
  },
  "receiver_id": {
    "$oid": "6648cbeb5161d66fd0e95f46"
  },
  "rating": 3
},
{
  "_id": {
    "$oid": "6648e345d81b52d5a2b8b847"
  },
  "sender_id": {
    "$oid": "6648cbeb5161d66fd0e95f16"
  },
  "receiver_id": {
    "$oid": "6648cbeb5161d66fd0e95f43"
  },
  "rating": 5
},
{
  "_id": {
    "$oid": "6648e345d81b52d5a2b8b848"
  },
  "sender_id": {
    "$oid": "6648cbec5161d66fd0e95f7c"
  },
  "receiver_id": {
    "$oid": "6648cbeb5161d66fd0e95f4d"
  },
  "rating": 1
},
{
  "_id": {
    "$oid": "6648e345d81b52d5a2b8b849"
  },
  "sender_id": {
    "$oid": "6648cbeb5161d66fd0e95f06"
  },
  "receiver_id": {
    "$oid": "6648cbeb5161d66fd0e95f4a"
  },
  "rating": 1
},
{
  "_id": {
    "$oid": "6648e345d81b52d5a2b8b84a"
  },
  "sender_id": {
    "$oid": "6648cbeb5161d66fd0e95f1b"
  },
  "receiver_id": {
    "$oid": "6648cbeb5161d66fd0e95f4d"
  },
  "rating": 5
},
{
  "_id": {
    "$oid": "6648e345d81b52d5a2b8b84b"
  },
  "sender_id": {
    "$oid": "6648cbec5161d66fd0e95f82"
  },
  "receiver_id": {
    "$oid": "6648cbeb5161d66fd0e95f3c"
  },
  "rating": 5
},
{
  "_id": {
    "$oid": "6648e345d81b52d5a2b8b84c"
  },
  "sender_id": {
    "$oid": "6648cbec5161d66fd0e95f87"
  },
  "receiver_id": {
    "$oid": "6648cbeb5161d66fd0e95f4f"
  },
  "rating": 4
},
{
  "_id": {
    "$oid": "6648e345d81b52d5a2b8b84d"
  },
  "sender_id": {
    "$oid": "6648cbec5161d66fd0e95f85"
  },
  "receiver_id": {
    "$oid": "6648cbeb5161d66fd0e95f51"
  },
  "rating": 2
},
{
  "_id": {
    "$oid": "6648e345d81b52d5a2b8b84e"
  },
  "sender_id": {
    "$oid": "6648cbec5161d66fd0e95f81"
  },
  "receiver_id": {
    "$oid": "6648cbeb5161d66fd0e95f56"
  },
  "rating": 4
},
{
  "_id": {
    "$oid": "6648e345d81b52d5a2b8b84f"
  },
  "sender_id": {
    "$oid": "6648cbeb5161d66fd0e95f15"
  },
  "receiver_id": {
    "$oid": "6648cbeb5161d66fd0e95f4f"
  },
  "rating": 4
},
{
  "_id": {
    "$oid": "6648e345d81b52d5a2b8b850"
  },
  "sender_id": {
    "$oid": "6648cbec5161d66fd0e95f89"
  },
  "receiver_id": {
    "$oid": "6648cbeb5161d66fd0e95f4e"
  },
  "rating": 5
},
{
  "_id": {
    "$oid": "6648e345d81b52d5a2b8b851"
  },
  "sender_id": {
    "$oid": "6648cbeb5161d66fd0e95f13"
  },
  "receiver_id": {
    "$oid": "6648cbeb5161d66fd0e95f4d"
  },
  "rating": 2
},
{
  "_id": {
    "$oid": "6648e345d81b52d5a2b8b852"
  },
  "sender_id": {
    "$oid": "6648cbec5161d66fd0e95f92"
  },
  "receiver_id": {
    "$oid": "6648cbeb5161d66fd0e95f42"
  },
  "rating": 5
},
{
  "_id": {
    "$oid": "6648e345d81b52d5a2b8b853"
  },
  "sender_id": {
    "$oid": "6648cbeb5161d66fd0e95f16"
  },
  "receiver_id": {
    "$oid": "6648cbeb5161d66fd0e95f40"
  },
  "rating": 2
},
{
  "_id": {
    "$oid": "6648e345d81b52d5a2b8b854"
  },
  "sender_id": {
    "$oid": "6648cbec5161d66fd0e95f77"
  },
  "receiver_id": {
    "$oid": "6648cbeb5161d66fd0e95f44"
  },
  "rating": 3
},
{
  "_id": {
    "$oid": "6648e345d81b52d5a2b8b855"
  },
  "sender_id": {
    "$oid": "6648cbeb5161d66fd0e95f04"
  },
  "receiver_id": {
    "$oid": "6648cbeb5161d66fd0e95f57"
  },
  "rating": 3
},
{
  "_id": {
    "$oid": "6648e345d81b52d5a2b8b856"
  },
  "sender_id": {
    "$oid": "6648cbeb5161d66fd0e95f02"
  },
  "receiver_id": {
    "$oid": "6648cbeb5161d66fd0e95f52"
  },
  "rating": 5
},
{
  "_id": {
    "$oid": "6648e345d81b52d5a2b8b857"
  },
  "sender_id": {
    "$oid": "6648cbeb5161d66fd0e95f16"
  },
  "receiver_id": {
    "$oid": "6648cbeb5161d66fd0e95f4c"
  },
  "rating": 4
},
{
  "_id": {
    "$oid": "6648e345d81b52d5a2b8b858"
  },
  "sender_id": {
    "$oid": "6648cbec5161d66fd0e95f8d"
  },
  "receiver_id": {
    "$oid": "6648cbeb5161d66fd0e95f4f"
  },
  "rating": 3
},
{
  "_id": {
    "$oid": "6648e345d81b52d5a2b8b859"
  },
  "sender_id": {
    "$oid": "6648cbec5161d66fd0e95f78"
  },
  "receiver_id": {
    "$oid": "6648cbeb5161d66fd0e95f43"
  },
  "rating": 3
},
{
  "_id": {
    "$oid": "6648e345d81b52d5a2b8b85a"
  },
  "sender_id": {
    "$oid": "6648cbec5161d66fd0e95f8a"
  },
  "receiver_id": {
    "$oid": "6648cbeb5161d66fd0e95f4a"
  },
  "rating": 3
},
{
  "_id": {
    "$oid": "6648e345d81b52d5a2b8b85b"
  },
  "sender_id": {
    "$oid": "6648cbeb5161d66fd0e95f00"
  },
  "receiver_id": {
    "$oid": "6648cbeb5161d66fd0e95f54"
  },
  "rating": 5
},
{
  "_id": {
    "$oid": "6648e345d81b52d5a2b8b85c"
  },
  "sender_id": {
    "$oid": "6648cbeb5161d66fd0e95f06"
  },
  "receiver_id": {
    "$oid": "6648cbeb5161d66fd0e95f43"
  },
  "rating": 2
},
{
  "_id": {
    "$oid": "6648e345d81b52d5a2b8b85d"
  },
  "sender_id": {
    "$oid": "6648cbeb5161d66fd0e95f02"
  },
  "receiver_id": {
    "$oid": "6648cbeb5161d66fd0e95f49"
  },
  "rating": 5
},
{
  "_id": {
    "$oid": "6648e345d81b52d5a2b8b85e"
  },
  "sender_id": {
    "$oid": "6648cbeb5161d66fd0e95f10"
  },
  "receiver_id": {
    "$oid": "6648cbeb5161d66fd0e95f44"
  },
  "rating": 2
},
{
  "_id": {
    "$oid": "6648e345d81b52d5a2b8b85f"
  },
  "sender_id": {
    "$oid": "6648cbeb5161d66fd0e95f0f"
  },
  "receiver_id": {
    "$oid": "6648cbeb5161d66fd0e95f4e"
  },
  "rating": 4
},
{
  "_id": {
    "$oid": "6648e345d81b52d5a2b8b860"
  },
  "sender_id": {
    "$oid": "6648cbec5161d66fd0e95f85"
  },
  "receiver_id": {
    "$oid": "6648cbeb5161d66fd0e95f3e"
  },
  "rating": 4
},
{
  "_id": {
    "$oid": "6648e345d81b52d5a2b8b861"
  },
  "sender_id": {
    "$oid": "6648cbeb5161d66fd0e95f03"
  },
  "receiver_id": {
    "$oid": "6648cbeb5161d66fd0e95f44"
  },
  "rating": 3
},
{
  "_id": {
    "$oid": "6648e345d81b52d5a2b8b862"
  },
  "sender_id": {
    "$oid": "6648cbeb5161d66fd0e95f16"
  },
  "receiver_id": {
    "$oid": "6648cbeb5161d66fd0e95f43"
  },
  "rating": 4
},
{
  "_id": {
    "$oid": "6648e345d81b52d5a2b8b863"
  },
  "sender_id": {
    "$oid": "6648cbec5161d66fd0e95f8e"
  },
  "receiver_id": {
    "$oid": "6648cbeb5161d66fd0e95f47"
  },
  "rating": 2
},
{
  "_id": {
    "$oid": "6648e345d81b52d5a2b8b864"
  },
  "sender_id": {
    "$oid": "6648cbec5161d66fd0e95f80"
  },
  "receiver_id": {
    "$oid": "6648cbeb5161d66fd0e95f4c"
  },
  "rating": 3
},
{
  "_id": {
    "$oid": "6648e345d81b52d5a2b8b865"
  },
  "sender_id": {
    "$oid": "6648cbeb5161d66fd0e95f19"
  },
  "receiver_id": {
    "$oid": "6648cbeb5161d66fd0e95f3d"
  },
  "rating": 2
},
{
  "_id": {
    "$oid": "6648e345d81b52d5a2b8b866"
  },
  "sender_id": {
    "$oid": "6648cbec5161d66fd0e95f7b"
  },
  "receiver_id": {
    "$oid": "6648cbeb5161d66fd0e95f4e"
  },
  "rating": 3
},
{
  "_id": {
    "$oid": "6648e345d81b52d5a2b8b867"
  },
  "sender_id": {
    "$oid": "6648cbec5161d66fd0e95f91"
  },
  "receiver_id": {
    "$oid": "6648cbeb5161d66fd0e95f51"
  },
  "rating": 2
},
{
  "_id": {
    "$oid": "6648e345d81b52d5a2b8b868"
  },
  "sender_id": {
    "$oid": "6648cbec5161d66fd0e95f7f"
  },
  "receiver_id": {
    "$oid": "6648cbeb5161d66fd0e95f58"
  },
  "rating": 5
},
{
  "_id": {
    "$oid": "6648e345d81b52d5a2b8b869"
  },
  "sender_id": {
    "$oid": "6648cbec5161d66fd0e95f80"
  },
  "receiver_id": {
    "$oid": "6648cbeb5161d66fd0e95f55"
  },
  "rating": 4
},
{
  "_id": {
    "$oid": "6648e345d81b52d5a2b8b86a"
  },
  "sender_id": {
    "$oid": "6648cbeb5161d66fd0e95f10"
  },
  "receiver_id": {
    "$oid": "6648cbeb5161d66fd0e95f3f"
  },
  "rating": 1
},
{
  "_id": {
    "$oid": "6648e345d81b52d5a2b8b86b"
  },
  "sender_id": {
    "$oid": "6648cbeb5161d66fd0e95f1a"
  },
  "receiver_id": {
    "$oid": "6648cbeb5161d66fd0e95f4b"
  },
  "rating": 5
},
{
  "_id": {
    "$oid": "6648e345d81b52d5a2b8b86c"
  },
  "sender_id": {
    "$oid": "6648cbec5161d66fd0e95f7a"
  },
  "receiver_id": {
    "$oid": "6648cbeb5161d66fd0e95f44"
  },
  "rating": 2
},
{
  "_id": {
    "$oid": "6648e345d81b52d5a2b8b86d"
  },
  "sender_id": {
    "$oid": "6648cbec5161d66fd0e95f84"
  },
  "receiver_id": {
    "$oid": "6648cbeb5161d66fd0e95f53"
  },
  "rating": 5
},
{
  "_id": {
    "$oid": "6648e345d81b52d5a2b8b86e"
  },
  "sender_id": {
    "$oid": "6648cbec5161d66fd0e95f7f"
  },
  "receiver_id": {
    "$oid": "6648cbeb5161d66fd0e95f3f"
  },
  "rating": 5
},
{
  "_id": {
    "$oid": "6648e345d81b52d5a2b8b86f"
  },
  "sender_id": {
    "$oid": "6648cbeb5161d66fd0e95f0a"
  },
  "receiver_id": {
    "$oid": "6648cbeb5161d66fd0e95f4d"
  },
  "rating": 1
},
{
  "_id": {
    "$oid": "6648e345d81b52d5a2b8b870"
  },
  "sender_id": {
    "$oid": "6648cbec5161d66fd0e95f8b"
  },
  "receiver_id": {
    "$oid": "6648cbeb5161d66fd0e95f3f"
  },
  "rating": 1
},
{
  "_id": {
    "$oid": "6648e345d81b52d5a2b8b871"
  },
  "sender_id": {
    "$oid": "6648cbeb5161d66fd0e95f0d"
  },
  "receiver_id": {
    "$oid": "6648cbeb5161d66fd0e95f57"
  },
  "rating": 1
},
{
  "_id": {
    "$oid": "6648e345d81b52d5a2b8b872"
  },
  "sender_id": {
    "$oid": "6648cbeb5161d66fd0e95f01"
  },
  "receiver_id": {
    "$oid": "6648cbeb5161d66fd0e95f53"
  },
  "rating": 3
},
{
  "_id": {
    "$oid": "66496f2d4ddada38a61224d1"
  },
  "sender_id": {
    "$oid": "6648cbeb5161d66fd0e95f00"
  },
  "receiver_id": {
    "$oid": "6648cbeb5161d66fd0e95f3b"
  },
  "rating": "5"
},
{
  "_id": {
    "$oid": "66496f704ddada38a61224d5"
  },
  "sender_id": {
    "$oid": "6648cbeb5161d66fd0e95f00"
  },
  "receiver_id": {
    "$oid": "6648cbeb5161d66fd0e95f3b"
  },
  "rating": "3"
},
{
  "_id": {
    "$oid": "66497d354ddada38a61224de"
  },
  "sender_id": {
    "$oid": "6648cbec5161d66fd0e95f77"
  },
  "receiver_id": {
    "$oid": "6648cbeb5161d66fd0e95f3b"
  },
  "rating": "3"
},
{
  "_id": {
    "$oid": "66497d894ddada38a61224e2"
  },
  "sender_id": {
    "$oid": "6648cbec5161d66fd0e95f77"
  },
  "receiver_id": {
    "$oid": "6648cbeb5161d66fd0e95f3b"
  },
  "rating": "3"
}]